CHANGES.txt
LICENSE.txt
MANIFEST.in
README.txt
__init__.py
_noise.h
_perlin.c
_simplex.c
perlin.py
setup.cfg
setup.py
shader.py
shader_noise.py
test.py
examples/1dnoise.py
examples/2dtexture.py
examples/animate_tex.py
examples/atmosphere.py
examples/bump.py
examples/earth.1024x512.jpg
examples/planet.py
noise_randomized.egg-info/PKG-INFO
noise_randomized.egg-info/SOURCES.txt
noise_randomized.egg-info/dependency_links.txt
noise_randomized.egg-info/top_level.txt